sass_embedded/__init__.py
sass_embedded/_const.py
sass_embedded/py.typed
sass_embedded/simple.py
sass_embedded/dart_sass/.gitignore
sass_embedded/dart_sass/__init__.py
sass_embedded/dart_sass/__main__.py
sass_embedded/dart_sass/installer.py
sass_embedded/protocol/__init__.py
sass_embedded/protocol/compiler.py
sass_embedded/protocol/embedded_sass_pb2.py
sass_embedded/protocol/embedded_sass_pb2.pyi
sass_embedded-0.1.3.dist-info/METADATA
sass_embedded-0.1.3.dist-info/WHEEL
sass_embedded-0.1.3.dist-info/RECORD
