Metadata-Version: 2.4
Name: sass-embedded
Version: 0.1.3
Summary: Sass/SCSS compile host using Dart Sass
Project-URL: Homepage, https://github.com/attakei/sass-embedded-python
Project-URL: Changelog, https://github.com/attakei/sass-embedded-python/blob/main/CHANGES.rst
Project-URL: Source, https://github.com/attakei/sass-embedded-python
Project-URL: Documentation, https://sass-embedded-python.readthedocs.io/stable/
Project-URL: Bug, https://github.com/attakei/sass-embedded-python/issues
Project-URL: Funding, https://github.com/sponsors/attakei
Author-email: Kazuya Takei <myself@attakei.net>
Classifier: Development Status :: 3 - Alpha
Classifier: Intended Audience :: Developers
Classifier: License :: OSI Approved
Classifier: License :: OSI Approved :: Apache Software License
Classifier: Operating System :: OS Independent
Classifier: Programming Language :: Python
Classifier: Programming Language :: Python :: 3
Classifier: Programming Language :: Python :: 3 :: Only
Classifier: Programming Language :: Python :: 3.9
Classifier: Programming Language :: Python :: 3.10
Classifier: Programming Language :: Python :: 3.11
Classifier: Programming Language :: Python :: 3.12
Classifier: Programming Language :: Python :: 3.13
Classifier: Topic :: Software Development :: Libraries
Classifier: Topic :: Utilities
Requires-Python: >=3.9
Requires-Dist: bbpb>=1.4.2
Requires-Dist: protobuf>=6
